collection_scanner/__init__.py
collection_scanner/counter.py
collection_scanner/scanner.py
collection_scanner/utils.py
collection_scanner/tests/__init__.py
collection_scanner-0.5.1.dist-info/LICENSE
collection_scanner-0.5.1.dist-info/METADATA
collection_scanner-0.5.1.dist-info/WHEEL
collection_scanner-0.5.1.dist-info/top_level.txt
collection_scanner-0.5.1.dist-info/RECORD
