Metadata-Version: 2.1
Name: collection-scanner
Version: 0.5.1
Summary: Scrapinghub Hubstorage Collection scanner.
Home-page: https://github.com/scrapinghub/collection-scanner
Maintainer: Scrapinghub
License: BSD
Classifier: Development Status :: 5 - Production/Stable
Classifier: Intended Audience :: Developers
Classifier: License :: OSI Approved :: BSD License
Classifier: Operating System :: OS Independent
Classifier: Programming Language :: Python :: 3.10
License-File: LICENSE
Requires-Dist: dateparser
Requires-Dist: retrying
Requires-Dist: scrapinghub (>=2.4.0)
